pytito/__about__.py
pytito/__init__.py
pytito/py.typed
pytito/admin/__init__.py
pytito/admin/_base_client.py
pytito/admin/account.py
pytito/admin/activity.py
pytito/admin/admin.py
pytito/admin/event.py
pytito/admin/py.typed
pytito/admin/release.py
pytito/admin/ticket.py
pytito-0.0.12.dist-info/licenses/LICENSE
pytito-0.0.12.dist-info/METADATA
pytito-0.0.12.dist-info/WHEEL
pytito-0.0.12.dist-info/top_level.txt
pytito-0.0.12.dist-info/RECORD
