Metadata-Version: 2.4
Name: pytito
Version: 0.0.12
Summary: Pythonic wrapper for the Tito IO API
Author: Keith Brady
License:                     GNU GENERAL PUBLIC LICENSE
Project-URL: Source, https://github.com/krcb197/python_tito_io_wrapper
Project-URL: Tracker, https://github.com/krcb197/python_tito_io_wrapper/issues
Project-URL: Documentation, https://github.com/krcb197/python_tito_io_wrapper
Project-URL: Changelog, https://github.com/krcb197/python_tito_io_wrapper/releases
Keywords: Python
Classifier: Development Status :: 3 - Alpha
Classifier: Programming Language :: Python
Classifier: Programming Language :: Python :: 3
Classifier: Programming Language :: Python :: 3.9
Classifier: Programming Language :: Python :: 3.10
Classifier: Programming Language :: Python :: 3.11
Classifier: Programming Language :: Python :: 3.12
Classifier: Programming Language :: Python :: 3.13
Classifier: Programming Language :: Python :: 3.14
Classifier: Programming Language :: Python :: 3 :: Only
Classifier: Intended Audience :: Developers
Classifier: License :: OSI Approved :: GNU General Public License v3 (GPLv3)
Classifier: Operating System :: OS Independent
Classifier: Typing :: Typed
Requires-Python: >=3.9.2
License-File: LICENSE
Requires-Dist: requests
Requires-Dist: StrEnum; python_version < "3.11"
Provides-Extra: dev
Requires-Dist: mypy; extra == "dev"
Requires-Dist: pylint; extra == "dev"
Requires-Dist: coverage; extra == "dev"
Requires-Dist: types-requests; extra == "dev"
Requires-Dist: pytest; extra == "dev"
Provides-Extra: unit-tests
Requires-Dist: pytest; extra == "unit-tests"
Requires-Dist: pytest-mock; extra == "unit-tests"
Requires-Dist: requests-mock; extra == "unit-tests"
Requires-Dist: Faker; extra == "unit-tests"
Provides-Extra: integration-tests
Requires-Dist: pytest; extra == "integration-tests"
Dynamic: license-file
